{"format":"fixedformat","path":"${STEP_THERAPY_DTL_FILE}","writeMode":"overwrite","description":"","fixedSchemaString":"record\n  string(\"\\x01\", maximum_length=100) step_therapy_group_name = NULL(\"\") ;\n  decimal(\"\\x01\",0, maximum_length=39) step_therapy_step_number = NULL(\"\") ;\n  bit_vector_t products;\nend ;","fixedSchemaJson":"","skipFooters":null,"schema":{"type":"struct","fields":[{"name":"step_therapy_group_name","type":"string","nullable":true,"metadata":{"description":"","mappings":[],"tags":[]}},{"name":"step_therapy_step_number","type":"string","nullable":true,"metadata":{"description":"","mappings":[],"tags":[]}},{"name":"products","type":"binary","nullable":true,"metadata":{"description":"","mappings":[],"tags":[]}}]},"skipHeaders":null,"componentInfo":{"gemId":"gitUri=http://gitserver:3000/DxEheDCJ_team_5751/DxEheDCJ_project_12651.git&subPath=&tag=0.1.2&projectSubscriptionProjectId=12651&path=gems/fixedformat","projectName":"ProphecySparkBasicsScala"},"datasetType":"File"}